{
    "hybrid_notepad_test": [
        {
            "action": "start-app",
            "target": "notepad.exe"
        },
        {
            "action": "wait",
            "target": "2"
        },
        {
            "action": "find-uia-id",
            "target": "15"
        },
        {
            "action": "type-uia",
            "target": "Hello from the UIA backend!"
        },
        {
            "action": "assert-uia-text",
            "target": "Hello from the UIA backend!"
        }
    ]
}